{"cameraMode":{"drawMode":0,"name":"Shaded","section":"Shading Mode"},"sceneLighting":true,"audioPlay":false,"sceneViewState":{"m_AlwaysRefresh":false,"showFog":true,"showSkybox":true,"showFlares":true,"showImageEffects":true,"showParticleSystems":true,"showVisualEffectGraphs":true,"m_FxEnabled":true},"in2DMode":false,"pivot":{"x":-0.6470890045166016,"y":0.053684234619140628,"z":5.114830493927002},"rotation":{"x":-0.1708296537399292,"y":0.7381823658943176,"z":-0.20335228741168977,"w":-0.6201229691505432},"size":10.0,"orthographic":false}